dns_checker/__init__.py
dns_checker/core.py
dns_checker-0.1.0.dist-info/licenses/LICENSE
dns_checker-0.1.0.dist-info/METADATA
dns_checker-0.1.0.dist-info/WHEEL
dns_checker-0.1.0.dist-info/entry_points.txt
dns_checker-0.1.0.dist-info/top_level.txt
dns_checker-0.1.0.dist-info/RECORD
