Metadata-Version: 2.4
Name: dns-checker
Version: 0.1.0
Summary: DNS record checker with IPv4/IPv6/SPF filtering
Author-email: Daniel <daniel@danielf.ch>
License: MIT
Requires-Python: >=3.7
License-File: LICENSE
Requires-Dist: dnspython>=2.4.2
Dynamic: license-file
